CHANGES.rst
MANIFEST.in
README.rst
setup.py
vorlauf.py
vorlauf.egg-info/PKG-INFO
vorlauf.egg-info/SOURCES.txt
vorlauf.egg-info/dependency_links.txt
vorlauf.egg-info/not-zip-safe
vorlauf.egg-info/requires.txt
vorlauf.egg-info/top_level.txt