Metadata-Version: 1.0
Name: vorlauf
Version: 1.0.0
Summary: Lightweight tool for piping subprocess processes to each other
Home-page: UNKNOWN
Author: Alex Holmes
Author-email: alex@alex-holmes.com
License: Apache Software License
Keywords: vorlauf subprocess pipe
Platform: UNKNOWN
